nickgenfast/__init__.py
nickgenfast/adjectives.txt
nickgenfast/nickgenfast.py
nickgenfast/nouns.txt
nickgenfast/verbs.txt
nickgenfast-0.0.3.dist-info/LICENCE
nickgenfast-0.0.3.dist-info/METADATA
nickgenfast-0.0.3.dist-info/WHEEL
nickgenfast-0.0.3.dist-info/top_level.txt
nickgenfast-0.0.3.dist-info/RECORD
