Metadata-Version: 2.1
Name: nickgenfast
Version: 0.0.3
Summary: A random nickname generator.
Home-page: https://github.com/BeLazy167/nickgenfast
Author: Dhruv Khara
Author-email: dhruvkhara167@gmail.com
Classifier: Programming Language :: Python :: 3
Classifier: License :: OSI Approved :: MIT License
Classifier: Operating System :: OS Independent
Requires-Python: >=3.6
License-File: LICENCE
